[{"__symbolic":"module","version":4,"metadata":{"FsPromptAutocompleteComponent":{"__symbolic":"class","decorators":[{"__symbolic":"call","expression":{"__symbolic":"reference","module":"@angular/core","name":"Component","line":9,"character":1},"arguments":[{"selector":"fs-prompt-autocomplete","templateUrl":"fs-prompt-autocomplete.component.html","styleUrls":["../fsprompt.css"]}]}],"members":{"__ctor__":[{"__symbolic":"constructor","parameterDecorators":[null,[{"__symbolic":"call","expression":{"__symbolic":"reference","module":"@angular/core","name":"Inject","line":25,"character":5},"arguments":[{"__symbolic":"reference","module":"@angular/material/dialog","name":"MAT_DIALOG_DATA","line":25,"character":12}]}]],"parameters":[{"__symbolic":"reference","module":"@angular/material/dialog","name":"MatDialogRef","line":24,"character":22,"arguments":[{"__symbolic":"reference","name":"FsPromptAutocompleteComponent"}]},{"__symbolic":"reference","name":"any"}]}],"ngOnInit":[{"__symbolic":"method"}],"complete":[{"__symbolic":"method"}],"setSelectedValue":[{"__symbolic":"method"}],"displayWith":[{"__symbolic":"method"}],"loadItems":[{"__symbolic":"method"}],"filterItems":[{"__symbolic":"method"}]}}}}]